setup.py
dag_dist/Binomialdistribution.py
dag_dist/Gaussiandistribution.py
dag_dist/Generaldistribution.py
dag_dist/__init__.py
dag_dist.egg-info/PKG-INFO
dag_dist.egg-info/SOURCES.txt
dag_dist.egg-info/dependency_links.txt
dag_dist.egg-info/not-zip-safe
dag_dist.egg-info/top_level.txt